cryptopix/__init__.py
cryptopix/cli.py
cryptopix/core/__init__.py
cryptopix/core/chromacrypt_kem.py
cryptopix/core/chromacrypt_sign.py
cryptopix/core/color_cipher.py
cryptopix/core/color_hash.py
cryptopix/core/lattice.py
cryptopix/core/optimizations.py
cryptopix/core/parameters.py
cryptopix/core/transforms.py
cryptopix/examples/__init__.py
cryptopix/examples/basic_usage.py
cryptopix/examples/benchmark.py
cryptopix/examples/demo.py
cryptopix/examples/quick_start.py
cryptopix/tests/__init__.py
cryptopix/tests/test_cipher.py
cryptopix/tests/test_hash.py
cryptopix/tests/test_kem.py
cryptopix/tests/test_signatures.py
cryptopix/tests/test_utils.py
cryptopix/utils/__init__.py
cryptopix/utils/performance.py
cryptopix/utils/serialization.py
cryptopix/utils/validation.py
cryptopix-8.0.0.dist-info/licenses/LICENSE
cryptopix-8.0.0.dist-info/METADATA
cryptopix-8.0.0.dist-info/WHEEL
cryptopix-8.0.0.dist-info/entry_points.txt
cryptopix-8.0.0.dist-info/top_level.txt
cryptopix-8.0.0.dist-info/RECORD
