Metadata-Version: 2.4
Name: cryptopix
Version: 8.0.0
Summary: Revolutionary Post-Quantum Cryptographic Library using Color Lattice Learning with Errors (CLWE)
Home-page: https://www.cryptopix.in
Author: CryptoPIX Team
Author-email: CryptoPIX Team <founder@cryptopix.in>
Maintainer-email: CryptoPIX Team <founder@cryptopix.in>
License-Expression: MIT
Project-URL: Homepage, https://www.cryptopix.in
Project-URL: Repository, https://github.com/cryptopix-official/cryptopix
Project-URL: Documentation, https://www.cryptopix.in/docs
Project-URL: Bug Tracker, https://github.com/cryptopix-official/cryptopix/issues
Project-URL: Changelog, https://github.com/cryptopix-official/cryptopix/blob/main/CHANGELOG.md
Project-URL: Support, https://www.cryptopix.in/support
Keywords: cryptography,post-quantum,lattice,color-based,encryption,signatures
Classifier: Development Status :: 4 - Beta
Classifier: Intended Audience :: Developers
Classifier: Intended Audience :: Science/Research
Classifier: Topic :: Security :: Cryptography
Classifier: Topic :: Scientific/Engineering :: Mathematics
Classifier: Programming Language :: Python :: 3
Classifier: Programming Language :: Python :: 3.8
Classifier: Programming Language :: Python :: 3.9
Classifier: Programming Language :: Python :: 3.10
Classifier: Programming Language :: Python :: 3.11
Classifier: Programming Language :: Python :: 3.12
Classifier: Operating System :: OS Independent
Requires-Python: >=3.8
License-File: LICENSE
Requires-Dist: numpy>=1.20.0
Requires-Dist: pillow>=8.0.0
Requires-Dist: cryptography>=3.4.0
Requires-Dist: setuptools>=75.3.2
Requires-Dist: scipy>=1.10.1
Requires-Dist: matplotlib>=3.7.5
Provides-Extra: dev
Requires-Dist: pytest>=6.0; extra == "dev"
Requires-Dist: pytest-cov>=2.0; extra == "dev"
Requires-Dist: pytest-benchmark>=3.4.0; extra == "dev"
Requires-Dist: black>=21.0; extra == "dev"
Requires-Dist: flake8>=3.8; extra == "dev"
Requires-Dist: mypy>=0.800; extra == "dev"
Requires-Dist: sphinx>=4.0; extra == "dev"
Requires-Dist: sphinx-rtd-theme>=1.0; extra == "dev"
Provides-Extra: fast
Requires-Dist: numba>=0.53.0; extra == "fast"
Requires-Dist: scipy>=1.7.0; extra == "fast"
Provides-Extra: gpu
Requires-Dist: cupy>=9.0.0; extra == "gpu"
Requires-Dist: numba>=0.53.0; extra == "gpu"
Provides-Extra: all
Requires-Dist: pytest>=6.0; extra == "all"
Requires-Dist: pytest-cov>=2.0; extra == "all"
Requires-Dist: pytest-benchmark>=3.4.0; extra == "all"
Requires-Dist: black>=21.0; extra == "all"
Requires-Dist: flake8>=3.8; extra == "all"
Requires-Dist: mypy>=0.800; extra == "all"
Requires-Dist: sphinx>=4.0; extra == "all"
Requires-Dist: sphinx-rtd-theme>=1.0; extra == "all"
Requires-Dist: numba>=0.53.0; extra == "all"
Requires-Dist: scipy>=1.7.0; extra == "all"
Requires-Dist: cupy>=9.0.0; extra == "all"
Dynamic: author
Dynamic: home-page
Dynamic: license-file
Dynamic: requires-python
